firex_flame_ui/COMMITHASH
firex_flame_ui/__init__.py
firex_flame_ui/_version.py
firex_flame_ui/index.html
firex_flame_ui/versioneer.py
firex_flame_ui/css/app.4cbebe45.css
firex_flame_ui/css/chunk-vendors.a2cbee8a.css
firex_flame_ui/img/firex_logo.675380cb.png
firex_flame_ui/js/app.b5cfde3d.js
firex_flame_ui/js/chunk-vendors.88295e09.js
firex_flame_ui-0.12.dist-info/LICENSE
firex_flame_ui-0.12.dist-info/METADATA
firex_flame_ui-0.12.dist-info/WHEEL
firex_flame_ui-0.12.dist-info/top_level.txt
firex_flame_ui-0.12.dist-info/zip-safe
firex_flame_ui-0.12.dist-info/RECORD
