Metadata-Version: 2.1
Name: firex-flame-ui
Version: 0.12
Summary: UI for FireX.
Home-page: https://github.com/FireXStuff/firex-flame-ui
Author: Core FireX Team
Author-email: firex-dev@gmail.com
License: BSD-3-Clause
Platform: UNKNOWN
